lib_pyclient/__init__.py
lib_pyclient/objectmethodresult.py
lib_pyclient/pyconvert.py
lib_pyclient/pywebapi.py
lib_pyclient/pywebapibase.py
lib_pyclient/test.py
lib_pyclient-0.0.6.dist-info/LICENSE.txt
lib_pyclient-0.0.6.dist-info/METADATA
lib_pyclient-0.0.6.dist-info/WHEEL
lib_pyclient-0.0.6.dist-info/entry_points.txt
lib_pyclient-0.0.6.dist-info/top_level.txt
lib_pyclient-0.0.6.dist-info/RECORD
