Metadata-Version: 2.1
Name: lib-pyclient
Version: 0.0.6
Summary: web api client 
Home-page: http://www.sonmicro.com/
Author: SonMicro Electronics
Author-email: info@sonmicro.com
License: MIT
